lev_tools/__init__.py
lev_tools/core.py
lev_tools/word_counter.py
lev_tools-0.0.2.dist-info/LICENSE
lev_tools-0.0.2.dist-info/METADATA
lev_tools-0.0.2.dist-info/WHEEL
lev_tools-0.0.2.dist-info/top_level.txt
lev_tools-0.0.2.dist-info/RECORD
