Metadata-Version: 2.1
Name: lev-tools
Version: 0.0.2
Summary: Tools created by Lev
Home-page: https://github.com/Levatius/word-counter
Author: Levatius
License: UNKNOWN
Platform: UNKNOWN
Classifier: Programming Language :: Python :: 3
Classifier: License :: OSI Approved :: MIT License
Classifier: Operating System :: OS Independent
Requires-Python: >=3.6
